README.md
sake
setup.py
master_sake.egg-info/PKG-INFO
master_sake.egg-info/SOURCES.txt
master_sake.egg-info/dependency_links.txt
master_sake.egg-info/requires.txt
master_sake.egg-info/top_level.txt
sakelib/__init__.py
sakelib/acts.py
sakelib/audit.py
sakelib/build.py
sakelib/constants.py